README.txt
setup.py
7lk_ocr_deploy.egg-info/PKG-INFO
7lk_ocr_deploy.egg-info/SOURCES.txt
7lk_ocr_deploy.egg-info/dependency_links.txt
7lk_ocr_deploy.egg-info/requires.txt
7lk_ocr_deploy.egg-info/top_level.txt
7lk_ocr_deploy.egg-info/zip-safe
libsvm/__init__.py
libsvm/svm.py
libsvm/svmutil.py
libsvm-source/svm-predict.c
libsvm-source/svm-scale.c
libsvm-source/svm-train.c
libsvm-source/svm.cpp
libsvm-source/svm.h