Metadata-Version: 1.1
Name: 7lk-ocr-deploy
Version: 0.1.69
Summary: Some deploy packages for ocr.
Home-page: http://blog.useasp.net/
Author: cjyfff
Author-email: youremail@email.com
License: MIT
Keywords: test python package
Platform: UNKNOWN
Classifier: License :: OSI Approved :: MIT License
Classifier: Programming Language :: Python
Classifier: Intended Audience :: Developers
Classifier: Operating System :: OS Independent
